[
    {
        "name": "Shahar Shenhar",
        "points": 21
    },
    {
        "name": "Patrick Chapin",
        "points": 27
    },
    {
        "name": "Stanislav Cifka",
        "points": 15
    },
    {
        "name": "Lars Dam",
        "points": 18
    },
    {
        "name": "Jeremy Dezani",
        "points": 15
    },
    {
        "name": "Reid Duke",
        "points": 12
    },
    {
        "name": "Willy Edel",
        "points": 12
    },
    {
        "name": "Ivan Floch",
        "points": 18
    },
    {
        "name": "Yuuki Ichikawa",
        "points": 18
    },
    {
        "name": "William Jensen",
        "points": 18
    },
    {
        "name": "Lee Shi Tian",
        "points": 9
    },
    {
        "name": "Raphael Levy",
        "points": 18
    },
    {
        "name": "Tom Martell",
        "points": 12
    },
    {
        "name": "Shaun McLaren",
        "points": 15
    },
    {
        "name": "Nam Sung Wook",
        "points": 9
    },
    {
        "name": "Raymond Perez Jr.",
        "points": 9
    },
    {
        "name": "Paulo Vitor Damo da Rosa",
        "points": 12
    },
    {
        "name": "Paul Rietzl",
        "points": 12
    },
    {
        "name": "Sam Black",
        "points": 21
    },
    {
        "name": "Owen Turtenwald",
        "points": 15
    },
    {
        "name": "Yuuya Watanabe",
        "points": 21
    },
    {
        "name": "Jacob Wilson",
        "points": 15
    },
    {
        "name": "Josh Utter-Leyton",
        "points": 15
    },
    {
        "name": "Kentarou Yamamoto",
        "points": 24
    }
]
